agl_report_reader/__init__.py
agl_report_reader/report_reader.py
agl_report_reader/settings.py
agl_report_reader/utils.py
agl_report_reader/anonymization/__init__.py
agl_report_reader/anonymization/names.py
agl_report_reader/anonymization/redact.py
agl_report_reader/extraction/__init__.py
agl_report_reader/extraction/examination_data.py
agl_report_reader/extraction/other_data.py
agl_report_reader/extraction/patient_data.py
agl_report_reader-0.4.0.dist-info/METADATA
agl_report_reader-0.4.0.dist-info/WHEEL
agl_report_reader-0.4.0.dist-info/licenses/LICENSE
agl_report_reader-0.4.0.dist-info/RECORD
